planQues/__init__.py
planQues/rabbitMq/__init__.py
planQues/rabbitMq/exchanges.py
planQues/rabbitMq/ques.py
planQues/rabbitMq/knative/KnativeLog.py
planQues/rabbitMq/knative/__init__.py
planQues/rabbitMq/utils/ConsumerService.py
planQues/rabbitMq/utils/ConsumerServiceOne.py
planQues/rabbitMq/utils/HeartBeat.py
planQues/rabbitMq/utils/HeartBeatService.py
planQues/rabbitMq/utils/MyFormatter.py
planQues/rabbitMq/utils/ProducerService.py
planQues/rabbitMq/utils/RabbitmqLogger.py
planQues/rabbitMq/utils/Service.py
planQues/rabbitMq/utils/__init__.py
planQues/rabbitMq/utils/service_utils.py
planQues-0.5.dist-info/METADATA
planQues-0.5.dist-info/WHEEL
planQues-0.5.dist-info/top_level.txt
planQues-0.5.dist-info/RECORD
